[{"name":"p_GGL500","mode":"2","isSmart":"","targets":{"google":{"limit":524288000,"usage":0}},"_id":"5fc7b6b6-583a-429f-9199-df707c5ff2ef"},{"name":"p_DBX500","mode":"1","isSmart":"","targets":{"dropbox":{"limit":524288000,"usage":0}},"_id":"860bd012-981f-4b2c-80f0-62bf7613ab84"},{"name":"p_GGL500","mode":"1","isSmart":"","targets":{"google":null,"dropbox":null},"_id":"253eb26f-1a89-49ee-93ff-3363912c900f"},{"name":"p_GGL500","mode":"1","isSmart":"","targets":{"google":{"limit":524288000,"usage":0}},"_id":"68e23719-fe10-4574-a54b-f566fbd3c617"},{"name":"p_MIX500EA","mode":"2","isSmart":"","targets":{"google":{"limit":524288000,"usage":0},"dropbox":{"limit":524288000,"usage":0}},"_id":"1192fdd8-c55e-4a09-8aea-23912a0dabe4"},{"name":"p_DBX500","mode":"1","isSmart":"","targets":{"dropbox":{"limit":524288000,"usage":0}},"_id":"5ba11198-c132-4025-a5d2-71999f99aa77"},{"name":"p_GGL200.0.0","mode":{"uploadType":"Partition RAID Type","isSmart":""},"targets":{"google":{"limit":209715200,"usage":0}},"blockWidth":2000,"_id":"bc05c824-bea5-449b-9585-c505bff4c069"},{"name":"p_GGL200SpanDumb","mode":{"uploadType":"1","isSmart":"1"},"targets":{"google":{"limit":209715200,"usage":0}},"blockWidth":2000,"_id":"f2eb6528-ccfa-489c-a45c-3f6ae3014b9a"},{"name":"p_GGL200SpanDumb","mode":{"uploadType":"1","isSmart":false},"targets":{"google":{"limit":209715200,"usage":0}},"blockWidth":2000,"_id":"57288593-51c6-482b-badf-92b67b1fa26f"},{"name":"p_GGLSpanDumb","mode":{"uploadType":"0","isSmart":false},"targets":{"google":{"limit":209715200,"usage":0}},"blockWidth":2000,"_id":"5694c2d0-407e-4c33-b8ea-c95288f409b1"},{"name":"p_GGLSpanDumb","mode":{"uploadType":0,"isSmart":false},"targets":{"google":{"limit":209715200,"usage":0}},"blockWidth":2000,"_id":"b39f594a-9a9c-489e-b2e5-082d2bfb43ce"},{"name":"p_DBXSpanDumb","mode":{"uploadType":0,"isSmart":false},"targets":{"dropbox":{"limit":209715200,"usage":0}},"blockWidth":2000,"_id":"108cf116-bea7-435f-b54b-4d970b3844b9"},{"name":"p_MIXSpan","mode":{"uploadType":0,"isSmart":false},"targets":{"google":{"limit":104857600,"usage":0},"dropbox":{"limit":104857600,"usage":0}},"blockWidth":2000,"_id":"22c59b5a-de74-443e-b54c-dcea2670f75c"},{"name":"p_MIXMirrorDumb","mode":{"uploadType":1,"isSmart":false},"targets":{"google":{"limit":52428800,"usage":0},"dropbox":{"limit":52428800,"usage":0}},"blockWidth":2000,"_id":"12f3a1de-c29b-41bd-bc48-ebe3a8e18c4b"},{"name":"p_GGLStipe","mode":{"uploadType":2,"isSmart":false},"targets":{"google":{"limit":209715200,"usage":0}},"blockWidth":2000,"_id":"0c557d4f-19e1-4a11-bb98-f0c6bba4eadb"},{"name":"p_DBXStripe","mode":{"uploadType":null,"isSmart":false},"targets":{"dropbox":{"limit":104857600,"usage":0}},"blockWidth":2000,"_id":"c42fb06f-3d0e-4e0f-a2bf-fcf9fe2b084e"},{"name":"p_DBXStripe","mode":{"uploadType":2,"isSmart":false},"targets":{"dropbox":{"limit":209715200,"usage":0}},"blockWidth":2000,"_id":"a99a2928-17ec-46a0-83f7-c1ddd80ae4dc"},{"name":"p_DBXStripeAgain","mode":{"uploadType":2,"isSmart":false},"targets":{"dropbox":{"limit":199229440,"usage":0}},"blockWidth":2000,"_id":"2b05d1f8-ae91-4a95-9fe9-744e29d777d8"},{"name":"p_GGLMirStrip","mode":{"uploadType":3,"isSmart":false},"targets":{"google":{"limit":104857600,"usage":0}},"blockWidth":2000,"_id":"32f55ca1-2794-41e9-9b4e-087496c4c65d"},{"name":"p_MixMirStrip","mode":{"uploadType":3,"isSmart":false},"targets":{"google":{"limit":104857600,"usage":0},"dropbox":{"limit":104857600,"usage":0}},"blockWidth":2000,"_id":"67417196-335c-4fc8-a42c-d85df461dcb6"},{"name":"p_ComboStripe","mode":{"uploadType":2,"isSmart":false},"targets":{"google":{"limit":104857600,"usage":0},"dropbox":{"limit":104857600,"usage":0}},"blockWidth":2000,"_id":"40d22f49-c9d8-4246-9aba-1e9cbb73acca"},{"name":"p_MirStripSmart","mode":{"uploadType":3,"isSmart":true},"targets":{"google":{"limit":209715200,"usage":0},"dropbox":{"limit":209715200,"usage":0}},"blockWidth":2000,"_id":"074df5e4-e377-44fa-a885-04eb1f7d7059"},{"name":"p_StripeSMart","mode":{"uploadType":2,"isSmart":true},"targets":{"google":{"limit":104857600,"usage":0},"dropbox":{"limit":104857600,"usage":0}},"blockWidth":2000,"_id":"424fc8dd-e80a-45bc-92a8-ed5b22a05302"},{"name":"p_","mode":{"uploadType":null,"isSmart":false},"targets":{},"blockWidth":2000,"_id":"49af2efd-0e46-485e-9f17-8de4f3630746"},{"name":"p_GGLSpan","mode":{"uploadType":0,"isSmart":false},"targets":{"google":{"limit":104857600,"usage":0}},"blockWidth":16384,"recoveryDensity":1,"_id":"239eff08-d3c2-4cd9-a08f-e804502d9a1a"},{"name":"p_DBXSpan","mode":{"uploadType":0,"isSmart":false},"targets":{"dropbox":{"limit":104857600,"usage":0}},"blockWidth":16384,"recoveryDensity":1,"_id":"6e9c22a0-f3b3-4bac-ad61-40cfe61d0d16"},{"name":"p_GGLDBXSpan","mode":{"uploadType":0,"isSmart":false},"targets":{"google":{"limit":104857600,"usage":0},"dropbox":{"limit":104857600,"usage":0}},"blockWidth":16384,"recoveryDensity":1,"_id":"262a222a-32e0-49d8-ae68-e92457c85a58"},{"name":"p_GGLDBXMir","mode":{"uploadType":1,"isSmart":false},"targets":{"google":{"limit":104857600,"usage":0},"dropbox":{"limit":104857600,"usage":0}},"blockWidth":16384,"recoveryDensity":1,"_id":"da930289-b08a-40d0-8976-27f1d0b6ad22"},{"name":"p_MixStripeDumb","mode":{"uploadType":2,"isSmart":false},"targets":{"google":{"limit":104857600,"usage":0},"dropbox":{"limit":104857600,"usage":0}},"blockWidth":16384,"recoveryDensity":1,"_id":"1dfb4b64-1343-4c83-b257-afe8dd2198b8"},{"name":"p_2KBStripeChunksize","mode":{"uploadType":2,"isSmart":false},"targets":{"google":{"limit":104857600,"usage":0},"dropbox":{"limit":104857600,"usage":0}},"blockWidth":16384,"recoveryDensity":1,"_id":"c52cee58-9c54-4da0-bcb7-e84469c7d183"},{"name":"p_2KBStripeMix","mode":{"uploadType":2,"isSmart":false},"targets":{"google":{"limit":104857600,"usage":0},"dropbox":{"limit":104857600,"usage":0}},"blockWidth":2048,"recoveryDensity":1,"_id":"b769fd47-97af-4cc5-9a60-42f73879642d"},{"name":"p_Stripe2kbMix","mode":{"uploadType":2,"isSmart":false},"targets":{"google":{"limit":104857600,"usage":0},"dropbox":{"limit":104857600,"usage":0}},"blockWidth":2048,"recoveryDensity":1,"_id":"2fc15ac2-b2b4-48ff-9211-d6f6dd54d9e2"},{"name":"p_span","mode":{"uploadType":0,"isSmart":false},"targets":{"google":{"limit":104857600,"usage":0},"dropbox":{"limit":104857600,"usage":0}},"blockWidth":16384,"recoveryDensity":1,"_id":"4d7007ec-c463-4d7a-ab89-8c7696115bd4"},{"name":"p_DBXOnly100","mode":{"uploadType":0,"isSmart":false},"targets":{"dropbox":{"limit":104857600,"usage":0}},"blockWidth":16384,"recoveryDensity":1,"_id":"20e180e0-beac-4dfb-85df-d310626c0a98"},{"name":"p_gglTest","mode":{"uploadType":0,"isSmart":false},"targets":{"google":{"limit":104857600,"usage":0}},"tracks":[],"isTracked":null,"blockWidth":16384,"recoveryDensity":1,"_id":"cdadf5e6-5525-4a02-b085-38a8150f780e"},{"name":"p_GGlTrackTest","mode":{"uploadType":0,"isSmart":false},"targets":{"google":{"limit":104857600,"usage":0}},"tracks":[],"isTracked":true,"blockWidth":16384,"recoveryDensity":1,"_id":"e57b15eb-6ce8-4d89-8a44-6da85ac93a0c"},{"name":"p_trackGGL","mode":{"uploadType":0,"isSmart":false},"targets":{"google":{"limit":104857600,"usage":0}},"tracks":[],"isTracked":false,"blockWidth":16384,"recoveryDensity":1,"_id":"2317b6c5-0d80-46f5-9bd8-5f5b22e48475"},{"name":"p_TrackGGL100","mode":{"uploadType":0,"isSmart":false},"targets":{"google":{"limit":104857600,"usage":0}},"tracks":[],"isTracked":true,"blockWidth":16384,"recoveryDensity":1,"_id":"af66109d-fdbc-4866-9754-2008c36e6c4b"},{"name":"p_tracked","mode":{"uploadType":0,"isSmart":false},"targets":{"google":{"limit":104857600,"usage":0}},"tracks":[],"isTracked":true,"blockWidth":16384,"recoveryDensity":1,"_id":"28d5118a-a084-4495-997d-1d2268953706"},{"name":"p_SmartTest","mode":{"uploadType":2,"isSmart":true},"targets":{"google":{"limit":104857600,"usage":0},"dropbox":{"limit":104857600,"usage":0}},"tracks":[],"isTracked":false,"blockWidth":16384,"recoveryDensity":1,"_id":"ba498981-f9b9-4e97-82ca-0bee6f8a5eb2"},{"name":"p_SpanSImple","mode":{"uploadType":0,"isSmart":false},"targets":{"google":{"limit":104857600,"usage":0}},"tracks":[],"isTracked":false,"blockWidth":16384,"recoveryDensity":1,"_id":"ea7dd981-efd2-4ee3-98d5-b96ee5ed8a86"}]